[
    {
        "id": 1,
        "name": "sun",
        "description": "Let's learn",
        "imgUrl": "https://i.pinimg.com/originals/41/6b/e9/416be9acd9944243b4a37261f77fa395.png",
        "url":"https://www.nasa.gov/kidsclub/index.html" 
    },
    {
        "id": 1,
        "name": "sun",
        "description": "Let's learn",
        "imgUrl": "https://66.media.tumblr.com/2fb5d62e11f684411f6805179b6dc608/tumblr_oik612SH651skktngo1_640.gifv",
        "url": "https://spaceplace.nasa.gov/sp/"
    },
    {
        "id": 1,
        "name": "sun",
        "description": "Let's learn, Let's learn, Let's learn, Let's learnLet's learnLet's learnLet's learnLet's learnLet's learnLet's learnLet's learnLet's learnLet's learnLet's learnLet's learnLet's learnLet's learnLet's learnLet's learnLet's learnLet's learnLet's learnLet's learn",
        "imgUrl": "https://gaptain.com/blog/wp-content/uploads/2018/12/esa-kids.jpg",
        "url": "https://www.esa.int/kids/es/Home"
    }
]